mrvbill/__init__.py
mrvbill/commands/bill_commands.py
mrvbill/commands/common_commands.py
mrvbill/decorators/provider.py
mrvbill/providers/harvest_provider.py
mrvbill/providers/provider.py
mrvbill/utils/date.py
mrvbill/utils/fs.py
mrvbill/utils/pdf.py
mrvbill-1.5.0.dist-info/LICENSE
mrvbill-1.5.0.dist-info/METADATA
mrvbill-1.5.0.dist-info/WHEEL
mrvbill-1.5.0.dist-info/entry_points.txt
mrvbill-1.5.0.dist-info/RECORD
