Metadata-Version: 2.1
Name: mrvbill
Version: 1.5.0
Summary: A command-line interface tool for managing bills and time tracking across different providers
Author: Rares Modure
Author-email: rares.modure@mrv-it.com
Requires-Python: >=3.13
Classifier: Programming Language :: Python :: 3
Classifier: Programming Language :: Python :: 3.13
Requires-Dist: aiohttp (>=3.9.3,<4.0.0)
Requires-Dist: click (>=8.1.8,<9.0.0)
Requires-Dist: pyfiglet (>=1.0.2,<2.0.0)
Requires-Dist: questionary (>=2.1.0,<3.0.0)
Requires-Dist: requests (>=2.32.3,<3.0.0)
Requires-Dist: rich (>=13.9.4,<14.0.0)
Requires-Dist: weasyprint (>=64.0,<65.0)
